CHANGES.txt
MANIFEST.in
README.txt
setup.py
fa/__init__.py
fa.bootstrap.egg-info/PKG-INFO
fa.bootstrap.egg-info/SOURCES.txt
fa.bootstrap.egg-info/dependency_links.txt
fa.bootstrap.egg-info/entry_points.txt
fa.bootstrap.egg-info/namespace_packages.txt
fa.bootstrap.egg-info/not-zip-safe
fa.bootstrap.egg-info/requires.txt
fa.bootstrap.egg-info/top_level.txt
fa/bootstrap/__init__.py
fa/bootstrap/actions.py
fa/bootstrap/fanstatic_resources.py
fa/bootstrap/renderers.py
fa/bootstrap/views.py
fa/bootstrap/scaffolds/__init__.py
fa/bootstrap/scaffolds/pyramid_fa_bootstrap/CHANGES.txt_tmpl
fa/bootstrap/scaffolds/pyramid_fa_bootstrap/README.txt_tmpl
fa/bootstrap/scaffolds/pyramid_fa_bootstrap/development.ini_tmpl
fa/bootstrap/scaffolds/pyramid_fa_bootstrap/production.ini_tmpl
fa/bootstrap/scaffolds/pyramid_fa_bootstrap/setup.cfg_tmpl
fa/bootstrap/scaffolds/pyramid_fa_bootstrap/setup.py_tmpl
fa/bootstrap/scaffolds/pyramid_fa_bootstrap/+package+/__init__.py_tmpl
fa/bootstrap/scaffolds/pyramid_fa_bootstrap/+package+/forms.py_tmpl
fa/bootstrap/scaffolds/pyramid_fa_bootstrap/+package+/models.py_tmpl
fa/bootstrap/scaffolds/pyramid_fa_bootstrap/+package+/routes.py_tmpl
fa/bootstrap/scaffolds/pyramid_fa_bootstrap/+package+/tests.py_tmpl
fa/bootstrap/scaffolds/pyramid_fa_bootstrap/+package+/views.py_tmpl
fa/bootstrap/scaffolds/pyramid_fa_bootstrap/+package+/static/footerbg.png
fa/bootstrap/scaffolds/pyramid_fa_bootstrap/+package+/static/headerbg.png
fa/bootstrap/scaffolds/pyramid_fa_bootstrap/+package+/static/ie6.css
fa/bootstrap/scaffolds/pyramid_fa_bootstrap/+package+/static/middlebg.png
fa/bootstrap/scaffolds/pyramid_fa_bootstrap/+package+/static/pylons.css
fa/bootstrap/scaffolds/pyramid_fa_bootstrap/+package+/static/pyramid-small.png
fa/bootstrap/scaffolds/pyramid_fa_bootstrap/+package+/static/pyramid.png
fa/bootstrap/scaffolds/pyramid_fa_bootstrap/+package+/static/transparent.gif
fa/bootstrap/scaffolds/pyramid_fa_bootstrap/+package+/templates/home.pt_tmpl
fa/bootstrap/scaffolds/pyramid_fa_bootstrap/+package+/templates/main_template.pt_tmpl
fa/bootstrap/static/js/autocomplete.js
fa/bootstrap/static/js/listing.js
fa/bootstrap/templates/admin/edit.pt
fa/bootstrap/templates/admin/listing.pt
fa/bootstrap/templates/admin/master.pt
fa/bootstrap/templates/admin/models.pt
