Metadata-Version: 1.0
Name: fa.bootstrap
Version: 0.3.3
Summary: pyramid_formalchemy twitter bootstrap integration
Home-page: https://github.com/RedTurtle/fa.bootstrap
Author: RedTurtle Developers
Author-email: svilplone@redturtle.it
License: GPL
Keywords: pyramid pyramid_formalchemy twitter bootstrap redturtle
Platform: UNKNOWN
Classifier: Programming Language :: Python
Classifier: Topic :: Software Development :: Libraries :: Python Modules
